phantasmpy/__init__.py
phantasmpy/client.py
phantasmpy/stubs/__init__.py
phantasmpy/stubs/receiver_pb2.py
phantasmpy/stubs/receiver_pb2_grpc.py
phantasmpy/types.py
phantasmpy-0.1.3.dist-info/METADATA
phantasmpy-0.1.3.dist-info/WHEEL
phantasmpy-0.1.3.dist-info/entry_points.txt
phantasmpy-0.1.3.dist-info/RECORD
