Metadata-Version: 2.1
Name: phantasmpy
Version: 0.1.3
Summary: A Python client to interact with Phantasm's receiver server.
Home-page: https://github.com/phantasmlabs/phantasm
License: MIT
Author: Edwin Kys
Author-email: edwin@phantasmlabs.com
Requires-Python: >=3.10,<4.0
Classifier: Intended Audience :: Developers
Classifier: Intended Audience :: System Administrators
Classifier: License :: OSI Approved :: MIT License
Classifier: Programming Language :: Python :: 3
Classifier: Programming Language :: Python :: 3.10
Classifier: Programming Language :: Python :: 3.11
Classifier: Programming Language :: Python :: 3.12
Classifier: Programming Language :: Python :: 3.13
Classifier: Topic :: Scientific/Engineering :: Artificial Intelligence
Classifier: Topic :: Scientific/Engineering :: Human Machine Interfaces
Classifier: Topic :: System :: Monitoring
Requires-Dist: black (>=24.10.0,<25.0.0)
Requires-Dist: grpcio (>=1.67.0,<2.0.0)
Requires-Dist: grpcio-tools (>=1.67.0,<2.0.0)
Project-URL: Issues, https://github.com/phantasmlabs/phantasm/issues
Project-URL: Repository, https://github.com/phantasmlabs/phantasm
